densenet/__init__.py
densenet/densenet.py
densenet-model/__init__.py
densenet-model/densenet.py
densenet-0.1.dist-info/LICENSE
densenet-0.1.dist-info/METADATA
densenet-0.1.dist-info/WHEEL
densenet-0.1.dist-info/top_level.txt
densenet-0.1.dist-info/RECORD
