Metadata-Version: 2.1
Name: densenet
Version: 0.1
Summary: A densenet implementation using tensorflow2
Home-page: https://github.com/okason97/DenseNet-Tensorflow2
Author: Gaston Gustavo Rios
Author-email: okason1997@hotmail.com
License: UNKNOWN
Platform: UNKNOWN
Classifier: Programming Language :: Python :: 3
Classifier: License :: OSI Approved :: MIT License
Classifier: Operating System :: OS Independent
Requires-Dist: tensorflow (==2.0.0-alpha0)
Requires-Dist: numpy
